hbl_card_payment/__init__.py
hbl_card_payment/card_payment.py
hbl_card_payment/utils.py
hbl_card_payment-0.0.3.dist-info/LICENSE
hbl_card_payment-0.0.3.dist-info/METADATA
hbl_card_payment-0.0.3.dist-info/WHEEL
hbl_card_payment-0.0.3.dist-info/top_level.txt
hbl_card_payment-0.0.3.dist-info/RECORD
