Metadata-Version: 2.1
Name: hbl-card-payment
Version: 0.0.3
Summary: A simple implementation of HBL card payment integration in Python.
Home-page: https://github.com/suzanpradhan/hbl_card_payment
Author: suzanpradhan
Author-email: sujanpradhan478@gmail.com
License: UNKNOWN
Platform: UNKNOWN
License-File: LICENSE
Requires-Dist: pyjwt
Requires-Dist: requests
Requires-Dist: python-jose
